MoonMag/__init__.py
MoonMag/asymmetry_funcs.py
MoonMag/config.py
MoonMag/eval_induced_field.py
MoonMag/field_xyz.py
MoonMag/plotting_funcs.py
MoonMag/run_all.py
MoonMag/symmetry_funcs.py
MoonMag/trajec_analysis.py
MoonMag/excitation/Be1xyz.txt
MoonMag/excitation/Be1xyz_Callisto.txt
MoonMag/excitation/Be1xyz_Europa.txt
MoonMag/excitation/Be1xyz_Miranda.txt
MoonMag/excitation/Be1xyz_Triton.txt
MoonMag/excitation/Be2xyz.txt
MoonMag/excitation/orbital_Be1xyz_Callisto.txt
MoonMag/excitation/orbital_Be1xyz_Europa.txt
MoonMag/excitation/orbital_Be1xyz_Miranda.txt
MoonMag/excitation/orbital_Be1xyz_Triton.txt
MoonMag/excitation/synodic_Be1xyz_Callisto.txt
MoonMag/excitation/synodic_Be1xyz_Europa.txt
MoonMag/excitation/synodic_Be1xyz_Miranda.txt
MoonMag/excitation/synodic_Be1xyz_Triton.txt
MoonMag/induced/Xid_values_n1_p10_np11.mat
MoonMag/induced/Xid_values_n1_p2_np3.mat
MoonMag/induced/Xid_values_n1_p4_np5.mat
MoonMag/induced/Xid_values_n1_p8_np9.mat
MoonMag/interior/degree1_shapes.txt
MoonMag/interior/degree1_shapes_Callisto.txt
MoonMag/interior/degree1_shapes_Europa_Tobie.txt
MoonMag/interior/degree1_shapes_Europa_prev.txt
MoonMag/interior/degree1_shapes_Miranda.txt
MoonMag/interior/degree1_shapes_Triton.txt
MoonMag/interior/degree2_shapes.txt
MoonMag/interior/degree2_shapes_Callisto.txt
MoonMag/interior/degree2_shapes_Europa_Tobie.txt
MoonMag/interior/degree2_shapes_Europa_prev.txt
MoonMag/interior/degree2_shapes_Miranda.txt
MoonMag/interior/degree2_shapes_Triton.txt
MoonMag/interior/degree3_shapes.txt
MoonMag/interior/degree3_shapes_Callisto.txt
MoonMag/interior/degree3_shapes_Europa_Tobie.txt
MoonMag/interior/degree3_shapes_Europa_prev.txt
MoonMag/interior/degree3_shapes_Miranda.txt
MoonMag/interior/degree3_shapes_Triton.txt
MoonMag/interior/degree4_shapes.txt
MoonMag/interior/degree4_shapes_Callisto.txt
MoonMag/interior/degree4_shapes_Europa_Tobie.txt
MoonMag/interior/degree4_shapes_Europa_prev.txt
MoonMag/interior/degree4_shapes_Miranda.txt
MoonMag-1.7.5.dist-info/LICENSE
MoonMag-1.7.5.dist-info/METADATA
MoonMag-1.7.5.dist-info/WHEEL
MoonMag-1.7.5.dist-info/top_level.txt
MoonMag-1.7.5.dist-info/RECORD
