Metadata-Version: 2.1
Name: MoonMag
Version: 1.7.5
Summary: Magnetic induction calculations for sounding of icy moons
Home-page: https://github.com/itsmoosh/MoonMag
Author: Marshall J. Styczinski
Author-email: marshall.styczinski@bmsis.org
Project-URL: Bug tracker, https://github.com/itsmoosh/MoonMag/issues
Project-URL: Original publication, https://doi.org/10.1016/j.icarus.2021.114840
Classifier: Programming Language :: Python :: 3.8
Classifier: License :: OSI Approved :: GNU General Public License v3 (GPLv3)
Classifier: Operating System :: OS Independent
License-File: LICENSE
Requires-Dist: numpy >=1.24.4
Requires-Dist: scipy >=1.11.4
Requires-Dist: mpmath >=1.3.0
Requires-Dist: matplotlib >=3.8.2
Requires-Dist: spiceypy >=6.0.0
